kbox/__init__.py
kbox/kbox-v0.0.2-alpha.jar
kbox/kbox.py
KBox-0.0.2a0.dist-info/LICENSE
KBox-0.0.2a0.dist-info/METADATA
KBox-0.0.2a0.dist-info/WHEEL
KBox-0.0.2a0.dist-info/entry_points.txt
KBox-0.0.2a0.dist-info/top_level.txt
KBox-0.0.2a0.dist-info/RECORD
