Metadata-Version: 2.1
Name: KBox
Version: 0.0.2a0
Summary: application will allow users to share and dereference ML models.
Home-page: https://github.com/AKSW/KBox/tree/master/kbox.pip
Author: Edgard Marx
Author-email: edgard.marx@htwk-leipzig.de
License: Apache
Platform: UNKNOWN
Classifier: License :: OSI Approved :: Apache Software License
Classifier: Programming Language :: Python :: 3
Requires-Dist: click (>=7.1.2)
